Workbook

Sheet Posiciones
A1: Ticker | B1: Broker | C1: Tipo | D1: Cantidad | E1: Coste (€) | F1: Precio Medio (€) | G1: Precio Actual (€) | H1: Valor Actual (€) | I1: P&L (€) | J1: P&L (%)
A2: BTC | B2: Kraken | C2: Crypto | D2: 0.05678 | E2: 1048.29 | F2: 18462.31 | G2: =IFERROR(GOOGLEFINANCE("BTCUSD","price")*GOOGLEFINANCE("CURRENCY:USDEUR"),0) | H2: =D2*G2 | I2: =H2-E2 | J2: =IF(E2>0,I2/E2,0)
A3: ETH | B3: Kraken | C3: Crypto | D3: 0.34793 | E3: 700.75 | F3: 2014.05 | G3: =IFERROR(GOOGLEFINANCE("ETHUSD","price")*GOOGLEFINANCE("CURRENCY:USDEUR"),0) | H3: =D3*G3 | I3: =H3-E3 | J3: =IF(E3>0,I3/E3,0)
A4: SOL | B4: Kraken | C4: Crypto | D4: 2.13768 | E4: 298.95 | F4: 139.85 | G4: =IFERROR(GOOGLEFINANCE("SOLUSD","price")*GOOGLEFINANCE("CURRENCY:USDEUR"),0) | H4: =D4*G4 | I4: =H4-E4 | J4: =IF(E4>0,I4/E4,0)
A5: NU | B5: Fintual | C5: Stock | D5: 91.449629 | E5: 1009.61 | F5: 11.04 | G5: =IFERROR(GOOGLEFINANCE("NU","price")*GOOGLEFINANCE("CURRENCY:USDEUR"),0) | H5: =D5*G5 | I5: =H5-E5 | J5: =IF(E5>0,I5/E5,0)
A6: AMZN | B6: Fintual | C6: Stock | D6: 5.998302 | E6: 1086.47 | F6: 181.13 | G6: =IFERROR(GOOGLEFINANCE("AMZN","price")*GOOGLEFINANCE("CURRENCY:USDEUR"),0) | H6: =D6*G6 | I6: =H6-E6 | J6: =IF(E6>0,I6/E6,0)
A7: SPY | B7: Fintual | C7: ETF | D7: 0.461054 | E7: 240.38 | F7: 521.37 | G7: =IFERROR(GOOGLEFINANCE("SPY","price")*GOOGLEFINANCE("CURRENCY:USDEUR"),0) | H7: =D7*G7 | I7: =H7-E7 | J7: =IF(E7>0,I7/E7,0)
A8: IEV | B8: Fintual | C8: ETF | D8: 20.544768 | E8: 1255.4 | F8: 61.11 | G8: =IFERROR(GOOGLEFINANCE("IEV","price")*GOOGLEFINANCE("CURRENCY:USDEUR"),0) | H8: =D8*G8 | I8: =H8-E8 | J8: =IF(E8>0,I8/E8,0)
A9: ARGT | B9: Fintual | C9: ETF | D9: 15.990136 | E9: 1356.09 | F9: 84.81 | G9: =IFERROR(GOOGLEFINANCE("ARGT","price")*GOOGLEFINANCE("CURRENCY:USDEUR"),0) | H9: =D9*G9 | I9: =H9-E9 | J9: =IF(E9>0,I9/E9,0)
A10: AAPL | B10: Fintual | C10: Stock | D10: 4.564051 | E10: 1193.89 | F10: 261.59 | G10: =IFERROR(GOOGLEFINANCE("AAPL","price")*GOOGLEFINANCE("CURRENCY:USDEUR"),0) | H10: =D10*G10 | I10: =H10-E10 | J10: =IF(E10>0,I10/E10,0)
A11: TOTAL | E11: =SUM(E2:E10) | H11: =SUM(H2:H10) | I11: =SUM(I2:I10) | J11: =IF(E11>0,I11/E11,0)

Sheet Dashboard
A1: PORTFOLIO - POSICIONES ABIERTAS
A2: Última actualización: | B2: =NOW()
A4: MÉTRICAS PRINCIPALES
A5: Métrica | B5: Valor
A6: Coste Total | B6: =Posiciones!E11
A7: Valor Actual | B7: =Posiciones!H11
A8: P&L | B8: =Posiciones!I11
A9: Rentabilidad | B9: =Posiciones!J11
A10: TIR Anualizada | B10: =IFERROR(XIRR(Flujos!B:B,Flujos!A:A),0)
A13: COMPOSICIÓN POR TIPO DE ACTIVO
A14: Tipo | B14: Coste (€) | C14: Valor Actual (€) | D14: P&L (€) | E14: Retorno Simple | F14: TIR
A15: Crypto | B15: =SUMIF(Posiciones!C:C,"Crypto",Posiciones!E:E) | C15: =SUMIF(Posiciones!C:C,"Crypto",Posiciones!H:H) | D15: =C15-B15 | E15: =IF(B15>0,D15/B15,0) | F15: =IFERROR(XIRR(Flujos_Crypto!B:B,Flujos_Crypto!A:A),"-")
A16: Stock | B16: =SUMIF(Posiciones!C:C,"Stock",Posiciones!E:E) | C16: =SUMIF(Posiciones!C:C,"Stock",Posiciones!H:H) | D16: =C16-B16 | E16: =IF(B16>0,D16/B16,0) | F16: =IFERROR(XIRR(Flujos_Stock!B:B,Flujos_Stock!A:A),"-")
A17: ETF | B17: =SUMIF(Posiciones!C:C,"ETF",Posiciones!E:E) | C17: =SUMIF(Posiciones!C:C,"ETF",Posiciones!H:H) | D17: =C17-B17 | E17: =IF(B17>0,D17/B17,0) | F17: =IFERROR(XIRR(Flujos_ETF!B:B,Flujos_ETF!A:A),"-")
A18: TOTAL | B18: =SUM(B15:B17) | C18: =SUM(C15:C17) | D18: =SUM(D15:D17) | E18: =IF(B18>0,D18/B18,0)
A21: COMPOSICIÓN POR BROKER
A22: Broker | B22: Coste (€) | C22: Valor Actual (€) | D22: P&L (€) | E22: Retorno Simple
A23: Kraken | B23: =SUMIF(Posiciones!B:B,"Kraken",Posiciones!E:E) | C23: =SUMIF(Posiciones!B:B,"Kraken",Posiciones!H:H) | D23: =C23-B23 | E23: =IF(B23>0,D23/B23,0)
A24: Fintual | B24: =SUMIF(Posiciones!B:B,"Fintual",Posiciones!E:E) | C24: =SUMIF(Posiciones!B:B,"Fintual",Posiciones!H:H) | D24: =C24-B24 | E24: =IF(B24>0,D24/B24,0)

Sheet Flujos
A1: Fecha | B1: Flujo (€) | C1: Concepto | D1: Tipo
A2: 2020-05-19 | B2: -248 | C2: Compra BTC | D2: Crypto
A3: 2021-05-19 | B3: -250 | C3: Compra BTC | D3: Crypto
A4: 2021-05-19 | B4: -250 | C4: Compra ETH | D4: Crypto
A5: 2021-12-03 | B5: -200 | C5: Compra SOL | D5: Crypto
A6: 2022-01-25 | B6: -196.46 | C6: Compra BTC | D6: Crypto
A7: 2022-01-25 | B7: -3.83 | C7: Compra BTC | D7: Crypto
A8: 2022-01-25 | B8: -300.75 | C8: Compra ETH | D8: Crypto
A9: 2022-01-25 | B9: -98.95 | C9: Compra SOL | D9: Crypto
A10: 2023-02-02 | B10: -150 | C10: Compra BTC | D10: Crypto
A11: 2023-02-02 | B11: -150 | C11: Compra ETH | D11: Crypto
A12: 2023-04-23 | B12: -200 | C12: Compra BTC | D12: Crypto
A13: 2025-12-18 | B13: -576.92 | C13: Compra NU | D13: Stock
... A21: 2026-01-01 | B21: -1193.89 | C21: Compra AAPL | D21: Stock
A22: =TODAY() | B22: =Posiciones!H11 | C22: Valor actual (para XIRR)

Sheet Flujos_Crypto
A1: Fecha | B1: Flujo (€)
A2: 2020-05-19 | B2: -248
A3: 2021-05-19 | B3: -250
A4: 2021-05-19 | B4: -250
A5: 2021-12-03 | B5: -200
A6: 2022-01-25 | B6: -196.46
A7: 2022-01-25 | B7: -3.83
A8: 2022-01-25 | B8: -300.75
A9: 2022-01-25 | B9: -98.95
A10: 2023-02-02 | B10: -150
A11: 2023-02-02 | B11: -150
A12: 2023-04-23 | B12: -200
A13: =TODAY() | B13: =SUMIF(Posiciones!C:C,"Crypto",Posiciones!H:H)

Sheet Flujos_Stock
A1: Fecha | B1: Flujo (€)
A2: 2025-12-18 | B2: -576.92
A3: 2025-12-18 | B3: -192.31
A4: 2025-12-18 | B4: -480.77
A5: 2025-12-18 | B5: -240.38
A6: 2025-12-18 | B6: -605.7
A7: 2026-01-01 | B7: -1193.89
A8: =TODAY() | B8: =SUMIF(Posiciones!C:C,"Stock",Posiciones!H:H)

Sheet Flujos_ETF
A1: Fecha | B1: Flujo (€)
A2: 2025-12-18 | B2: -240.38
A3: 2025-12-18 | B3: -1255.4
A4: 2025-12-18 | B4: -1356.09
A5: =TODAY() | B5: =SUMIF(Posiciones!C:C,"ETF",Posiciones!H:H)

Sheet Calendario
A1: Mes | B1: Kraken (€) | C1: Fintual (€) | D1: Total (€)
A2: 2020-05 | B2: 248 | C2: 0 | D2: =B2+C2
A3: 2021-05 | B3: 500 | C3: 0 | D3: =B3+C3
A4: 2021-12 | B4: 200 | C4: 0 | D4: =B4+C4
A5: 2022-01 | B5: 599.99 | C5: 0 | D5: =B5+C5
A6: 2023-02 | B6: 300 | C6: 0 | D6: =B6+C6
A7: 2023-04 | B7: 200 | C7: 0 | D7: =B7+C7
A8: 2025-12 | B8: 0 | C8: 4947.95 | D8: =B8+C8
A9: 2026-01 | B9: 0 | C9: 1193.89 | D9: =B9+C9
A10: TOTAL | B10: =SUM(B2:B9) | C10: =SUM(C2:C9) | D10: =SUM(D2:D9)
